{
  "id": "task_022",
  "title": "Moisture reading SOP schedule",
  "description": "create moisture reading SOP and implement moisture readings schedule",
  "status": "todo",
  "priority": "medium",
  "created": "2026-02-11T01:52:57Z",
  "updated": "2026-02-11T02:55:11Z",
  "assignee": "",
  "involved_people": [],
  "updates": [
    {
      "date": "2026-02-11T02:55:11Z",
      "description": "Calibrated the moisture meter today",
      "creator": "system"
    }
  ],
  "frequency": "",
  "next_occurrence": ""
}